django_babel_boilerplate/__init__.py
django_babel_boilerplate/command_line.py
django_babel_boilerplate-0.0.7.dist-info/LICENSE
django_babel_boilerplate-0.0.7.dist-info/METADATA
django_babel_boilerplate-0.0.7.dist-info/WHEEL
django_babel_boilerplate-0.0.7.dist-info/entry_points.txt
django_babel_boilerplate-0.0.7.dist-info/top_level.txt
django_babel_boilerplate-0.0.7.dist-info/RECORD
