Metadata-Version: 2.1
Name: django-babel-boilerplate
Version: 0.0.7
Summary: A package which create django babel boilerplate.
Home-page: https://github.com/Navaneeth-Nagesh/django-babel-boilerplate
Author: Navaneeth Nagesh
Author-email: navaneethnagesh56@gmail.com
License: UNKNOWN
Keywords: Django,babel,sass
Platform: UNKNOWN
Classifier: Programming Language :: Python :: 3
Classifier: License :: OSI Approved :: MIT License
Classifier: Operating System :: OS Independent
Requires-Dist: Django (>=2.0.0)
Requires-Dist: django-inline-svg (>=0.1.1)
